wwuaggregator/__init__.py
wwuaggregator-1.0.0.dist-info/LICENSE
wwuaggregator-1.0.0.dist-info/METADATA
wwuaggregator-1.0.0.dist-info/WHEEL
wwuaggregator-1.0.0.dist-info/top_level.txt
wwuaggregator-1.0.0.dist-info/RECORD
