Metadata-Version: 2.1
Name: wwuaggregator
Version: 1.0.0
Summary: Aggregator for producing reporting datasets
Home-page: https://github.com/wwu-edu/wwuaggregator
Author: Western Washington University
Author-email: OIE@wwu.edu
Project-URL: Bug Tracker, https://github.com/wwu-edu/wwuaggregator/issues
Classifier: Programming Language :: Python :: 3
Classifier: License :: OSI Approved :: MIT License
Classifier: Operating System :: OS Independent
Requires-Python: >=3.6
License-File: LICENSE
Requires-Dist: polars
